pyminioadmin/__init__.py
pyminioadmin-0.2.dist-info/METADATA
pyminioadmin-0.2.dist-info/WHEEL
pyminioadmin-0.2.dist-info/top_level.txt
pyminioadmin-0.2.dist-info/RECORD
