Metadata-Version: 2.1
Name: pyminioadmin
Version: 0.2
Summary: A Python library for the MinIO admin client
Author: Iuri Peniche
Author-email: iuripeniche@hotmail.com
